vineyard/contrib/ray/__init__.py
vineyard/contrib/ray/actor.py
vineyard/contrib/ray/dataset.py
vineyard_ray-0.6.1.dist-info/LICENSE
vineyard_ray-0.6.1.dist-info/METADATA
vineyard_ray-0.6.1.dist-info/NOTICE.txt
vineyard_ray-0.6.1.dist-info/WHEEL
vineyard_ray-0.6.1.dist-info/top_level.txt
vineyard_ray-0.6.1.dist-info/RECORD
